Metadata-Version: 1.1
Name: dtool-gui-tk
Version: 0.4.0
Summary: Graphical user interface for managing data using dtool
Home-page: https://github.com/jic-dtool/dtool-gui-tk
Author: Tjelvar Olsson
Author-email: tjelvar.olsson@jic.ac.uk
License: MIT
Download-URL: https://github.com/jic-dtool/dtool-gui-tk/tarball/0.4.0
Platform: UNKNOWN
